[{
  "title": "Custard Pie",
  "length": "4:15"
}, {
  "title": "The Rover",
  "length": "5:39"
}, {
  "title": "In My Time Of Dying",
  "length": "11:08"
}, {
  "title": "Houses Of The Holy",
  "length": "4:04"
}, {
  "title": "Trampled Under Foot",
  "length": "5:36"
}, {
  "title": "Kashmir",
  "length": "8:37"
}, {
  "title": "In The Light",
  "length": "8:47"
}, {
  "title": "Bron-Yr-Aur",
  "length": "2:06"
}, {
  "title": "Down By The Seaside",
  "length": "5:15"
}, {
  "title": "Ten Years Gone",
  "length": "6:34"
}, {
  "title": "Night Flight",
  "length": "3:38"
}, {
  "title": "The Wanton Song",
  "length": "4:08"
}, {
  "title": "Boogie With Stu",
  "length": "3:52"
}, {
  "title": "Black Country Woman",
  "length": "4:24"
}, {
  "title": "Sick Again",
  "length": "4:42"
}]
